{
  "date": "2026-05-30",
  "time": "20:51",
  "timestamp": "2026-05-30T20:51+00:00",
  "url": "https://public.websites-dev.eu-central-1.kncloud.aws.int.kn/",
  "mobile": {
    "scores": {
      "performance": 71,
      "accessibility": 90,
      "best-practices": 100,
      "seo": 54
    },
    "cwv": {
      "LCP": "4.7 s",
      "INP": null,
      "CLS": "0",
      "FCP": "3.2 s",
      "TTFB": "Root document took 320 ms"
    }
  },
  "desktop": {
    "scores": {
      "performance": 96,
      "accessibility": 94,
      "best-practices": 100,
      "seo": 54
    },
    "cwv": {
      "LCP": "1.2 s",
      "INP": null,
      "CLS": "0.002",
      "FCP": "0.7 s",
      "TTFB": "Root document took 10 ms"
    }
  }
}